control_unit.sv
module control_unit (input logic[3:0] opcode,
                    output logic Branch, ALUSrc, RegWrite,
                    output logic[1:0]ALUControl);
always_comb
case (opcode)
    4'b0000 : begin
        RegWrite = 1; ALUSrc = 0; ALUControl = 2'b00; Branch = 0;
    end
    4'b0001 : begin
        RegWrite = 1; ALUSrc = 0; ALUControl = 2'b01; Branch = 0;
    end
    4'b0010 : begin
        RegWrite = 1; ALUSrc = 0; ALUControl = 2'b10; Branch = 0;
    end
    4'b0011 : begin
        RegWrite = 1; ALUSrc = 0; ALUControl = 2'b11; Branch = 0;
    end
    4'b0100 : begin
        RegWrite = 1; ALUSrc = 1; ALUControl = 2'b00; Branch = 0;
    end
    4'b0101 : begin
        RegWrite = 1; ALUSrc = 1; ALUControl = 2'b01; Branch = 0;
    end
    4'b0110 : begin
        RegWrite = 1; ALUSrc = 1; ALUControl = 2'b10; Branch = 0;
    end
    4'b0111 : begin
        RegWrite = 0; ALUSrc = 0; ALUControl = 2'b11; Branch = 1;
    end

endcase
endmodule

control_unit_tb.sv
`timescale 1ps/1ps
`include "control_unit.sv"

module control_unit_tb;
logic[3:0] t_opcode;
logic t_Branch, t_ALUSrc, t_RegWrite;
logic [1:0] t_ALUControl;

control_unit dut (t_opcode, t_Branch, t_ALUSrc, t_RegWrite, t_ALUControl);

initial begin
    $dumpfile("control_unit_tb.vcd"); 
    $dumpvars(0, control_unit_tb);
    // Stimulus generator
    t_opcode = 4'b0000;
    #20 t_opcode = 4'b0001;
    #20 t_opcode = 4'b0010;
    #20 t_opcode = 4'b0011;
    #20 t_opcode = 4'b0100;
    #20 t_opcode = 4'b0101;
    #20 t_opcode = 4'b0110;
    #20 t_opcode = 4'b0111;
end

initial begin // Response monitor
    $monitor ("t = %3d t_opcode = %b, t_RegWrite = %d, t_ALUSrc = %d, ALUControl = %b, Branch = %d", $time, t_opcode, t_RegWrite, t_ALUSrc, t_ALUControl, t_Branch);
end
endmodule

control_unit_tb.vcd
$date
	Sun Feb 19 12:51:54 2023
$end
$version
	Icarus Verilog
$end
$timescale
	1ps
$end
$scope module control_unit_tb $end
$var wire 1 ! t_RegWrite $end
$var wire 1 " t_Branch $end
$var wire 1 # t_ALUSrc $end
$var wire 2 $ t_ALUControl [1:0] $end
$var reg 4 % t_opcode [3:0] $end
$scope module dut $end
$var wire 4 & opcode [3:0] $end
$var reg 2 ' ALUControl [1:0] $end
$var reg 1 # ALUSrc $end
$var reg 1 " Branch $end
$var reg 1 ! RegWrite $end
$upscope $end
$upscope $end
$enddefinitions $end
#0
$dumpvars
b0 '
b0 &
b0 %
b0 $
0#
0"
1!
$end
#20
b1 $
b1 '
b1 %
b1 &
#40
b10 $
b10 '
b10 %
b10 &
#60
b11 $
b11 '
b11 %
b11 &
#80
b0 $
b0 '
1#
b100 %
b100 &
#100
b1 $
b1 '
b101 %
b101 &
#120
b10 $
b10 '
b110 %
b110 &
#140
1"
b11 $
b11 '
0#
0!
b111 %
b111 &
