control_unit.sv
module control_unit (input logic[3:0] opcode,
                    output logic Branch, ALUSrc, RegWrite,
                    output logic[1:0]ALUControl);
always_comb
case (opcode)
    4'b0000 : begin
        RegWrite = 1; ALUSrc = 0; ALUControl = 2'b00; Branch = 0;
    end
    4'b0001 : begin
        RegWrite = 1; ALUSrc = 0; ALUControl = 2'b01; Branch = 0;
    end
    4'b0010 : begin
        RegWrite = 1; ALUSrc = 0; ALUControl = 2'b10; Branch = 0;
    end
    4'b0011 : begin
        RegWrite = 1; ALUSrc = 0; ALUControl = 2'b11; Branch = 0;
    end
    4'b0100 : begin
        RegWrite = 1; ALUSrc = 1; ALUControl = 2'b00; Branch = 0;
    end
    4'b0101 : begin
        RegWrite = 1; ALUSrc = 1; ALUControl = 2'b01; Branch = 0;
    end
    4'b0110 : begin
        RegWrite = 1; ALUSrc = 1; ALUControl = 2'b10; Branch = 0;
    end
    4'b0111 : begin
        RegWrite = 0; ALUSrc = 0; ALUControl = 2'b11; Branch = 1;
    end

endcase
endmodule

reg_file.sv
module reg_file(input logic [3:0] RA1, RA2, WA, 
                        input logic [7:0] ALUResult,
                        input logic clk, write_enable,
                        output logic [7:0] RD1, RD2, cpu_out); 
logic [7:0] rf [0:15];
logic [3:0] zero;

assign RD1 = rf[RA1]; 
assign RD2 = rf[RA2]; 
assign cpu_out = rf[15];

assign rf[0] == 8'h0;

always_ff @(posedge clk) 
if (write_enable && WA > 0) 
    rf[WA] = ALUResult;

endmodule

alu.sv
module alu(input logic [7:0] SrcA,
            input logic [7:0] SrcB,
            input logic [1:0] ALUControl,
            output logic [7:0] ALUResult,
            output logic Zero);

always_comb
case (ALUControl)
2'b00 : ALUResult = SrcA & SrcB;
2'b01 : ALUResult = SrcA | SrcB;
2'b10 : ALUResult = SrcA + SrcB;
2'b11 : ALUResult = SrcA - SrcB;
default : ALUResult = 8'bx;
endcase

assign Zero = (ALUResult == 8'b0);

endmodule

reg_file_alu.sv
`include "reg_file.sv"
`include "alu.sv"

module reg_file_alu(input logic [3:0] RA1, RA2, WA,
                    input logic [7:0] immediate,
                    input logic [1:0] ALUControl,
                    input logic write_enable, ALUSrc, CLK,
                    output logic [7:0] ALUResult, cpu_out,
                    output logic Zero);
logic[7:0] x_srcA, x_srcB, x_RD2;

alu newalu(x_srcA, x_srcB, ALUControl, ALUResult, Zero);
reg_file newregfile(RA1, RA2, WA, ALUResult, CLK, write_enable, x_srcA, x_RD2, cpu_out);
// 2 to 1 multiplexer
assign x_srcB = (ALUSrc) ? immediate : x_RD2;

endmodule

instruction_memory.sv
module instruction_memory(input logic[7:0] PC,
                        output logic[23:0] Instr);
logic [23:0] data_ROM [0:255];
initial
$readmemh("program.txt", data_ROM); 
assign Instr = data_ROM[PC]; 
endmodule

pc.sv
module pc (input logic[7:0] immediate, 
            input logic PCSrc, CLK, reset,
            output logic[7:0] PC);
always_ff @ (posedge CLK) begin
    if (reset) PC <= 8'b0; 
    else if (PCSrc) PC <= immediate;
    else PC <= PC + 1; 
end
endmodule

instruction_memory_pc.sv
`include "instruction_memory.sv"
`include "pc.sv"

module instruction_memory_pc (input logic[7:0] immediate,
                            input logic PCSrc, CLK, reset,
                            output logic [23:0] Instr);
logic[7:0] x_PC;             

pc new_pc (immediate, PCSrc, CLK, reset, x_PC);
instruction_memory new_im(x_PC, Instr);
endmodule

cpu.sv
`include "control_unit.sv"
`include "reg_file_alu.sv"
`include "instruction_memory_pc.sv"

module cpu (input logic CLK, reset,
            output logic[7:0] ALUResult, cpu_out);
logic x_PCSrc;
logic [23:0] x_Instr;
logic [1:0] x_ALUControl;
logic x_ALUSrc, x_RegWrite, x_Branch, x_Zero;


instruction_memory_pc cpu_instruction_memory_pc(x_Instr[7:0], x_PCSrc, CLK, reset, 
    x_Instr);

reg_file_alu cpu_reg_file_alu (x_Instr[15:12], x_Instr[11:8], x_Instr[19:16], x_Instr[7:0], x_ALUControl, x_RegWrite, x_ALUSrc, CLK, 
    ALUResult, cpu_out, x_Zero);

control_unit cpu_control_unit (x_Instr[23:20], x_Branch, x_ALUSrc, x_RegWrite, x_ALUControl);

assign x_PCSrc = x_Branch & x_Zero;

endmodule

cpu_tb.sv
`timescale 1ps/1ps
`include "cpu.sv"

module cpu_tb;
logic clk, t_reset;
logic [7:0] t_ALUResult, t_cpu_out;

cpu dut (clk, t_reset, t_ALUResult, t_cpu_out);

initial begin
    clk = 0;
    forever #10 clk = ~clk;
end

initial begin
    $dumpfile("cpu_tb.vcd"); 
    $dumpvars(0, cpu_tb);
    // Stimulus generator
    t_reset = 1; 
    #20 t_reset = 0;
    #1000 $finish;
end

initial begin // Response monitor
    $monitor ("t = %3d clk = %d, t_reset = %d t_ALUResult = %b t_cpu_out = %d", $time, clk, t_reset, t_ALUResult, t_cpu_out);
end
endmodule

cpu_tb.vcd
$date
	Sun Feb 19 17:17:04 2023
$end
$version
	Icarus Verilog
$end
$timescale
	1ps
$end
$scope module cpu_tb $end
$var wire 8 ! t_cpu_out [7:0] $end
$var wire 8 " t_ALUResult [7:0] $end
$var reg 1 # clk $end
$var reg 1 $ t_reset $end
$scope module dut $end
$var wire 1 # CLK $end
$var wire 1 $ reset $end
$var wire 1 % x_PCSrc $end
$var wire 1 & x_Zero $end
$var wire 1 ' x_RegWrite $end
$var wire 24 ( x_Instr [23:0] $end
$var wire 1 ) x_Branch $end
$var wire 1 * x_ALUSrc $end
$var wire 2 + x_ALUControl [1:0] $end
$var wire 8 , cpu_out [7:0] $end
$var wire 8 - ALUResult [7:0] $end
$scope module cpu_control_unit $end
$var wire 4 . opcode [3:0] $end
$var reg 2 / ALUControl [1:0] $end
$var reg 1 * ALUSrc $end
$var reg 1 ) Branch $end
$var reg 1 ' RegWrite $end
$upscope $end
$scope module cpu_instruction_memory_pc $end
$var wire 1 # CLK $end
$var wire 1 % PCSrc $end
$var wire 8 0 immediate [7:0] $end
$var wire 1 $ reset $end
$var wire 8 1 x_PC [7:0] $end
$var wire 24 2 Instr [23:0] $end
$scope module new_im $end
$var wire 24 3 Instr [23:0] $end
$var wire 8 4 PC [7:0] $end
$upscope $end
$scope module new_pc $end
$var wire 1 # CLK $end
$var wire 1 % PCSrc $end
$var wire 8 5 immediate [7:0] $end
$var wire 1 $ reset $end
$var reg 8 6 PC [7:0] $end
$upscope $end
$upscope $end
$scope module cpu_reg_file_alu $end
$var wire 2 7 ALUControl [1:0] $end
$var wire 1 * ALUSrc $end
$var wire 1 # CLK $end
$var wire 4 8 RA1 [3:0] $end
$var wire 4 9 RA2 [3:0] $end
$var wire 4 : WA [3:0] $end
$var wire 8 ; immediate [7:0] $end
$var wire 1 ' write_enable $end
$var wire 8 < x_srcB [7:0] $end
$var wire 8 = x_srcA [7:0] $end
$var wire 8 > x_RD2 [7:0] $end
$var wire 8 ? cpu_out [7:0] $end
$var wire 1 & Zero $end
$var wire 8 @ ALUResult [7:0] $end
$scope module newalu $end
$var wire 2 A ALUControl [1:0] $end
$var wire 8 B SrcB [7:0] $end
$var wire 1 & Zero $end
$var wire 8 C SrcA [7:0] $end
$var reg 8 D ALUResult [7:0] $end
$upscope $end
$scope module newregfile $end
$var wire 8 E ALUResult [7:0] $end
$var wire 4 F RA1 [3:0] $end
$var wire 4 G RA2 [3:0] $end
$var wire 8 H RD1 [7:0] $end
$var wire 8 I RD2 [7:0] $end
$var wire 4 J WA [3:0] $end
$var wire 1 # clk $end
$var wire 8 K cpu_out [7:0] $end
$var wire 1 ' write_enable $end
$upscope $end
$upscope $end
$upscope $end
$upscope $end
$enddefinitions $end
#0
$dumpvars
bx K
bx J
bx I
bx H
bx G
bx F
bx E
bx D
bx C
bx B
bx A
bx @
bx ?
bx >
bx =
bx <
bx ;
bx :
bx 9
bx 8
bx 7
bx 6
bx 5
bx 4
bx 3
bx 2
bx 1
bx 0
bx /
bx .
bx -
bx ,
bx +
x*
x)
bx (
x'
x&
x%
1$
0#
bx "
bx !
$end
#10
0&
b1 "
b1 -
b1 @
b1 D
b1 E
0%
0)
b10 +
b10 /
b10 7
b10 A
1*
1'
b1 <
b1 B
b110 .
b1 ;
b1 :
b1 J
b0 >
b0 I
b0 9
b0 G
b0 =
b0 C
b0 H
b0 8
b0 F
b1 0
b1 5
b11000010000000000000001 (
b11000010000000000000001 2
b11000010000000000000001 3
b0 1
b0 4
b0 6
1#
#20
0#
0$
#30
b100000 "
b100000 -
b100000 @
b100000 D
b100000 E
b100000 <
b100000 B
b100000 ;
b10 :
b10 J
b100000 0
b100000 5
b11000100000000000100000 (
b11000100000000000100000 2
b11000100000000000100000 3
b1 1
b1 4
b1 6
1#
#40
0#
#50
1&
b0 "
b0 -
b0 @
b0 D
b0 E
b0 <
b0 B
b0 ;
b1111 :
b1111 J
b0 0
b0 5
b11011110000000000000000 (
b11011110000000000000000 2
b11011110000000000000000 3
b10 1
b10 4
b10 6
1#
#60
0#
#70
1)
b11 +
b11 /
b11 7
b11 A
0*
0'
b100000 <
b100000 B
0&
b11100001 "
b11100001 -
b11100001 @
b11100001 D
b11100001 E
b111 .
b111 ;
b0 :
b0 J
b100000 >
b100000 I
b10 9
b10 G
b1 =
b1 C
b1 H
b1 8
b1 F
b111 0
b111 5
b0 !
b0 ,
b0 ?
b0 K
b11100000001001000000111 (
b11100000001001000000111 2
b11100000001001000000111 3
b11 1
b11 4
b11 6
1#
#80
0#
#90
b10 "
b10 -
b10 @
b10 D
b10 E
0)
b10 +
b10 /
b10 7
b10 A
1'
b1 <
b1 B
b10 .
b0 ;
b1 :
b1 J
b1 >
b1 I
b1 9
b1 G
b0 0
b0 5
b1000010001000100000000 (
b1000010001000100000000 2
b1000010001000100000000 3
b100 1
b100 4
b100 6
1#
#100
0#
#110
1*
0&
b1 "
b1 -
b1 @
b1 D
b1 E
b1 <
b1 B
b110 .
b1 ;
b1111 :
b1111 J
b0 9
b0 G
b1111 8
b1111 F
b1 0
b1 5
b0 =
b0 C
b0 H
b0 >
b0 I
b11011111111000000000001 (
b11011111111000000000001 2
b11011111111000000000001 3
b101 1
b101 4
b101 6
1#
#120
0#
#130
1%
1&
1)
b11 +
b11 /
b11 7
b11 A
0*
0'
b0 <
b0 B
b111 .
b11 ;
b0 :
b0 J
b0 8
b0 F
b11 0
b11 5
b0 "
b0 -
b0 @
b0 D
b0 E
b11100000000000000000011 (
b11100000000000000000011 2
b11100000000000000000011 3
b110 1
b110 4
b110 6
b0 =
b0 C
b0 H
b1 !
b1 ,
b1 ?
b1 K
1#
#140
0#
#150
0%
b100000 <
b100000 B
0&
b11100010 "
b11100010 -
b11100010 @
b11100010 D
b11100010 E
b111 ;
b100000 >
b100000 I
b10 9
b10 G
b10 =
b10 C
b10 H
b1 8
b1 F
b111 0
b111 5
b11100000001001000000111 (
b11100000001001000000111 2
b11100000001001000000111 3
b11 1
b11 4
b11 6
1#
#160
0#
#170
b100 "
b100 -
b100 @
b100 D
b100 E
0)
b10 +
b10 /
b10 7
b10 A
1'
b10 <
b10 B
b10 .
b0 ;
b1 :
b1 J
b10 >
b10 I
b1 9
b1 G
b0 0
b0 5
b1000010001000100000000 (
b1000010001000100000000 2
b1000010001000100000000 3
b100 1
b100 4
b100 6
1#
#180
0#
#190
1*
b10 "
b10 -
b10 @
b10 D
b10 E
b1 <
b1 B
b110 .
b1 ;
b1111 :
b1111 J
b0 9
b0 G
b1111 8
b1111 F
b1 0
b1 5
b1 =
b1 C
b1 H
b0 >
b0 I
b11011111111000000000001 (
b11011111111000000000001 2
b11011111111000000000001 3
b101 1
b101 4
b101 6
1#
#200
0#
#210
1%
1&
1)
b11 +
b11 /
b11 7
b11 A
0*
0'
b0 <
b0 B
b111 .
b11 ;
b0 :
b0 J
b0 8
b0 F
b11 0
b11 5
b0 "
b0 -
b0 @
b0 D
b0 E
b11100000000000000000011 (
b11100000000000000000011 2
b11100000000000000000011 3
b110 1
b110 4
b110 6
b0 =
b0 C
b0 H
b10 !
b10 ,
b10 ?
b10 K
1#
#220
0#
#230
0%
b100000 <
b100000 B
0&
b11100100 "
b11100100 -
b11100100 @
b11100100 D
b11100100 E
b111 ;
b100000 >
b100000 I
b10 9
b10 G
b100 =
b100 C
b100 H
b1 8
b1 F
b111 0
b111 5
b11100000001001000000111 (
b11100000001001000000111 2
b11100000001001000000111 3
b11 1
b11 4
b11 6
1#
#240
0#
#250
b1000 "
b1000 -
b1000 @
b1000 D
b1000 E
0)
b10 +
b10 /
b10 7
b10 A
1'
b100 <
b100 B
b10 .
b0 ;
b1 :
b1 J
b100 >
b100 I
b1 9
b1 G
b0 0
b0 5
b1000010001000100000000 (
b1000010001000100000000 2
b1000010001000100000000 3
b100 1
b100 4
b100 6
1#
#260
0#
#270
1*
b11 "
b11 -
b11 @
b11 D
b11 E
b1 <
b1 B
b110 .
b1 ;
b1111 :
b1111 J
b0 9
b0 G
b1111 8
b1111 F
b1 0
b1 5
b10 =
b10 C
b10 H
b0 >
b0 I
b11011111111000000000001 (
b11011111111000000000001 2
b11011111111000000000001 3
b101 1
b101 4
b101 6
1#
#280
0#
#290
1%
1&
1)
b11 +
b11 /
b11 7
b11 A
0*
0'
b0 <
b0 B
b111 .
b11 ;
b0 :
b0 J
b0 8
b0 F
b11 0
b11 5
b0 "
b0 -
b0 @
b0 D
b0 E
b11100000000000000000011 (
b11100000000000000000011 2
b11100000000000000000011 3
b110 1
b110 4
b110 6
b0 =
b0 C
b0 H
b11 !
b11 ,
b11 ?
b11 K
1#
#300
0#
#310
0%
b100000 <
b100000 B
0&
b11101000 "
b11101000 -
b11101000 @
b11101000 D
b11101000 E
b111 ;
b100000 >
b100000 I
b10 9
b10 G
b1000 =
b1000 C
b1000 H
b1 8
b1 F
b111 0
b111 5
b11100000001001000000111 (
b11100000001001000000111 2
b11100000001001000000111 3
b11 1
b11 4
b11 6
1#
#320
0#
#330
b10000 "
b10000 -
b10000 @
b10000 D
b10000 E
0)
b10 +
b10 /
b10 7
b10 A
1'
b1000 <
b1000 B
b10 .
b0 ;
b1 :
b1 J
b1000 >
b1000 I
b1 9
b1 G
b0 0
b0 5
b1000010001000100000000 (
b1000010001000100000000 2
b1000010001000100000000 3
b100 1
b100 4
b100 6
1#
#340
0#
#350
1*
b100 "
b100 -
b100 @
b100 D
b100 E
b1 <
b1 B
b110 .
b1 ;
b1111 :
b1111 J
b0 9
b0 G
b1111 8
b1111 F
b1 0
b1 5
b11 =
b11 C
b11 H
b0 >
b0 I
b11011111111000000000001 (
b11011111111000000000001 2
b11011111111000000000001 3
b101 1
b101 4
b101 6
1#
#360
0#
#370
1%
1&
1)
b11 +
b11 /
b11 7
b11 A
0*
0'
b0 <
b0 B
b111 .
b11 ;
b0 :
b0 J
b0 8
b0 F
b11 0
b11 5
b0 "
b0 -
b0 @
b0 D
b0 E
b11100000000000000000011 (
b11100000000000000000011 2
b11100000000000000000011 3
b110 1
b110 4
b110 6
b0 =
b0 C
b0 H
b100 !
b100 ,
b100 ?
b100 K
1#
#380
0#
#390
0%
b100000 <
b100000 B
0&
b11110000 "
b11110000 -
b11110000 @
b11110000 D
b11110000 E
b111 ;
b100000 >
b100000 I
b10 9
b10 G
b10000 =
b10000 C
b10000 H
b1 8
b1 F
b111 0
b111 5
b11100000001001000000111 (
b11100000001001000000111 2
b11100000001001000000111 3
b11 1
b11 4
b11 6
1#
#400
0#
#410
b100000 "
b100000 -
b100000 @
b100000 D
b100000 E
0)
b10 +
b10 /
b10 7
b10 A
1'
b10000 <
b10000 B
b10 .
b0 ;
b1 :
b1 J
b10000 >
b10000 I
b1 9
b1 G
b0 0
b0 5
b1000010001000100000000 (
b1000010001000100000000 2
b1000010001000100000000 3
b100 1
b100 4
b100 6
1#
#420
0#
#430
1*
b101 "
b101 -
b101 @
b101 D
b101 E
b1 <
b1 B
b110 .
b1 ;
b1111 :
b1111 J
b0 9
b0 G
b1111 8
b1111 F
b1 0
b1 5
b100 =
b100 C
b100 H
b0 >
b0 I
b11011111111000000000001 (
b11011111111000000000001 2
b11011111111000000000001 3
b101 1
b101 4
b101 6
1#
#440
0#
#450
1%
1&
1)
b11 +
b11 /
b11 7
b11 A
0*
0'
b0 <
b0 B
b111 .
b11 ;
b0 :
b0 J
b0 8
b0 F
b11 0
b11 5
b0 "
b0 -
b0 @
b0 D
b0 E
b11100000000000000000011 (
b11100000000000000000011 2
b11100000000000000000011 3
b110 1
b110 4
b110 6
b0 =
b0 C
b0 H
b101 !
b101 ,
b101 ?
b101 K
1#
#460
0#
#470
1%
b100000 <
b100000 B
1&
b0 "
b0 -
b0 @
b0 D
b0 E
b111 ;
b100000 >
b100000 I
b10 9
b10 G
b100000 =
b100000 C
b100000 H
b1 8
b1 F
b111 0
b111 5
b11100000001001000000111 (
b11100000001001000000111 2
b11100000001001000000111 3
b11 1
b11 4
b11 6
1#
#480
0#
#490
1%
b0 <
b0 B
1&
b0 "
b0 -
b0 @
b0 D
b0 E
b0 >
b0 I
b0 9
b0 G
b0 =
b0 C
b0 H
b0 8
b0 F
b11100000000000000000111 (
b11100000000000000000111 2
b11100000000000000000111 3
b111 1
b111 4
b111 6
1#
