instruction_memory.sv
module instruction_memory(input logic[7:0] PC,
                        output logic[23:0] Instr);
logic [23:0] data_ROM [0:255];
initial
$readmemh("program.txt", data_ROM); 
assign Instr = data_ROM[PC]; 
endmodule

instruction_memory_tb.sv
`timescale 1ns/1ps 
`include "instruction_memory.sv"

module instruction_memory_tb;
logic [7:0] t_PC;
logic [23:0] t_Instr;

instruction_memory dut (t_PC, t_Instr);

initial begin
    $dumpfile("instruction_memory_tb.vcd"); 
    $dumpvars(0, instruction_memory_tb);
    // Stimulus generator
    t_PC = 8'h00; 
    #10 t_PC = 8'h01;
    #10 t_PC = 8'h02;
    #10 t_PC = 8'h03;
    #10 t_PC = 8'h04;
    #10 t_PC = 8'h05;
    #10 t_PC = 8'h06;
    #10 t_PC = 8'h07;
    
end

initial begin // Response monitor
    $monitor ("t_PC = %h t_Instr = %h", t_PC, t_Instr);
end

endmodule

instruction_memory_tb.vcd
$date
	Sun Feb 19 11:52:43 2023
$end
$version
	Icarus Verilog
$end
$timescale
	1ps
$end
$scope module instruction_memory_tb $end
$var wire 24 ! t_Instr [23:0] $end
$var reg 8 " t_PC [7:0] $end
$scope module dut $end
$var wire 24 # Instr [23:0] $end
$var wire 8 $ PC [7:0] $end
$upscope $end
$upscope $end
$enddefinitions $end
#0
$dumpvars
b0 $
b11000010000000000000001 #
b0 "
b11000010000000000000001 !
$end
#10000
b11000100000000000100000 !
b11000100000000000100000 #
b1 "
b1 $
#20000
b11011110000000000000000 !
b11011110000000000000000 #
b10 "
b10 $
#30000
b11100000001001000000111 !
b11100000001001000000111 #
b11 "
b11 $
#40000
b1000010001000100000000 !
b1000010001000100000000 #
b100 "
b100 $
#50000
b11011111111000000000001 !
b11011111111000000000001 #
b101 "
b101 $
#60000
b11100000000000000000011 !
b11100000000000000000011 #
b110 "
b110 $
#70000
b11100000000000000000111 !
b11100000000000000000111 #
b111 "
b111 $
