pc.sv
module pc (input logic[7:0] immediate, 
            input logic PCSrc, CLK, reset,
            output logic[7:0] PC);
always_ff @ (posedge CLK) begin
    if (reset) PC <= 8'b0; 
    else if (PCSrc) PC <= immediate;
    else PC <= PC + 1; 
end
endmodule

pc_tb.sv
`timescale 1ns/1ps
`include "pc.sv"

module pc_tb;
logic [7:0] t_PC, t_immediate;
logic t_PCSrc, clk, t_reset;


pc pc(t_immediate, t_PCSrc, clk, t_reset, t_PC);

initial begin
    clk = 0;
    forever #10 clk = ~clk;
end

initial begin
    $dumpfile("pc_tb.vcd"); 
    $dumpvars(0, pc_tb);
    // Stimulus generator
    t_reset = 1; t_PCSrc = 0; t_immediate = 8'b01;
    #10;
    t_reset = 0; t_PCSrc = 1;
    #20
    t_immediate = 8'b111;
    #20
    t_PCSrc = 0;
    #50
    t_reset = 1;
    #20;
end

initial begin // Response monitor
    $monitor ("t = %3d clk = %d, t_immediate = %b t_PCSrc = %b t_reset = %d t_PC = %d", $time, clk, t_immediate, t_PCSrc, t_reset, t_PC);
    #120;
    $finish; 
end

endmodule

pc_tb.vcd
$date
	Sat Feb 18 20:15:06 2023
$end
$version
	Icarus Verilog
$end
$timescale
	1ps
$end
$scope module pc_tb $end
$var wire 8 ! t_PC [7:0] $end
$var reg 1 " clk $end
$var reg 1 # t_PCSrc $end
$var reg 8 $ t_immediate [7:0] $end
$var reg 1 % t_reset $end
$scope module pc $end
$var wire 1 " CLK $end
$var wire 1 # PCSrc $end
$var wire 8 & immediate [7:0] $end
$var wire 1 % reset $end
$var reg 8 ' PC [7:0] $end
$upscope $end
$upscope $end
$enddefinitions $end
#0
$dumpvars
bx '
b1 &
1%
b1 $
0#
0"
bx !
$end
#10000
b1 !
b1 '
1#
0%
1"
#20000
0"
#30000
b111 !
b111 '
1"
b111 $
b111 &
#40000
0"
#50000
b1000 !
b1000 '
1"
0#
#60000
0"
#70000
b1001 !
b1001 '
1"
#80000
0"
#90000
b1010 !
b1010 '
1"
#100000
0"
1%
#110000
b0 !
b0 '
1"
