reg_file_exp.sv
module reg_file_exp(input logic [3:0] RA1, RA2, WA, input logic [7:0] data_in,
input logic clk, reset, write_enable,
output logic [7:0] data_out1, data_out2); logic [7:0] rf [0:15];
assign data_out1 = rf[RA1]; assign data_out2 = rf[RA2]; always_ff @ (posedge clk)
if (write_enable)
rf[WA] <= data_in;
endmodule

reg_file_exp_tb.sv

`timescale 1ps/1ps 
`include "reg_file_exp.sv"
module reg_file_exp_tb;
logic [3:0] RA1, RA2, WA;
logic clk, reset, write_enable;
logic [7:0] data_in, data_out1, data_out2;
reg_file_exp dut (RA1, RA2, WA, data_in, clk, reset, write_enable, data_out1, data_out2);
initial begin // Generate clock signal with 20 ns period 
clk = 0;
forever #10 clk = ~clk;
end
initial begin // Apply stimulus 
$dumpfile("reg_file_exp_tb.vcd");
$dumpvars(0, reg_file_exp_tb);
RA1 = 1; RA2 = 2; WA = 0; data_in = 5; write_enable = 0; reset = 1;
#10 reset = 0;
#15 write_enable = 1;
#20 WA = 1; data_in = 7;
#20 WA = 5; data_in = 13;
#20 write_enable = 0;
#20 RA2 = 5;
#30;
$finish; // This system tasks ends the simulation 
end
initial begin // Response monitor
$monitor ("t = %3d, clk = %b, reset = %b, RA1 = %b RA2 = %b WA = %b, write_enable = %b, data_in = %b, data_out1 = %b, data_out2 = %b ", $time, clk, reset, RA1, RA2, WA, write_enable, data_in, data_out1, data_out2); 
end
endmodule

reg_file_exp_tb.vcd
$date
	Fri Feb 17 19:07:09 2023
$end
$version
	Icarus Verilog
$end
$timescale
	1ps
$end
$scope module reg_file_exp_tb $end
$var wire 8 ! data_out2 [7:0] $end
$var wire 8 " data_out1 [7:0] $end
$var reg 4 # RA1 [3:0] $end
$var reg 4 $ RA2 [3:0] $end
$var reg 4 % WA [3:0] $end
$var reg 1 & clk $end
$var reg 8 ' data_in [7:0] $end
$var reg 1 ( reset $end
$var reg 1 ) write_enable $end
$scope module dut $end
$var wire 4 * RA1 [3:0] $end
$var wire 4 + RA2 [3:0] $end
$var wire 4 , WA [3:0] $end
$var wire 1 & clk $end
$var wire 8 - data_in [7:0] $end
$var wire 8 . data_out1 [7:0] $end
$var wire 8 / data_out2 [7:0] $end
$var wire 1 ( reset $end
$var wire 1 ) write_enable $end
$upscope $end
$upscope $end
$enddefinitions $end
#0
$dumpvars
bx /
bx .
b101 -
b0 ,
b10 +
b1 *
0)
1(
b101 '
0&
b0 %
b10 $
b1 #
bx "
bx !
$end
#10
0(
1&
#20
0&
#25
1)
#30
1&
#40
0&
#45
b111 '
b111 -
b1 %
b1 ,
#50
b111 "
b111 .
1&
#60
0&
#65
b1101 '
b1101 -
b101 %
b101 ,
#70
1&
#80
0&
#85
0)
#90
1&
#100
0&
#105
b1101 !
b1101 /
b101 $
b101 +
