reg_file.sv
module reg_file(input logic [3:0] RA1, RA2, WA, 
                input logic [7:0] ALUResult,
                input logic clk, write_enable,
                output logic [7:0] RD1, RD2, cpu_out); 
logic [7:0] rf [0:15];

assign RD1 = rf[RA1]; 
assign RD2 = rf[RA2]; 
assign cpu_out = rf[15];

initial begin
    rf[4'b0] = 8'b0;
end

always_ff @(posedge clk) 
if (write_enable && WA > 0) 
    rf[WA] <= ALUResult;

endmodule

alu.sv
module alu(input logic [7:0] SrcA,
            input logic [7:0] SrcB,
            input logic [1:0] ALUControl,
            output logic [7:0] ALUResult,
            output logic Zero);

always_comb
case (ALUControl)
2'b00 : ALUResult = SrcA & SrcB;
2'b01 : ALUResult = SrcA | SrcB;
2'b10 : ALUResult = SrcA + SrcB;
2'b11 : ALUResult = SrcA - SrcB;
default : ALUResult = 8'bx;
endcase

assign Zero = (ALUResult == 8'b0);

endmodule

reg_file_alu.sv
`include "reg_file.sv"
`include "alu.sv"

module reg_file_alu(input logic [3:0] RA1, RA2, WA,
                    input logic [7:0] immediate,
                    input logic [1:0] ALUControl,
                    input logic write_enable, ALUSrc, CLK,
                    output logic [7:0] ALUResult, cpu_out,
                    output logic Zero);
logic[7:0] x_srcA, x_srcB, x_RD2;

alu newalu(x_srcA, x_srcB, ALUControl, ALUResult, Zero);
reg_file newregfile(RA1, RA2, WA, ALUResult, CLK, write_enable, x_srcA, x_RD2, cpu_out);
// 2 to 1 multiplexer
assign x_srcB = (ALUSrc) ? immediate : x_RD2;

endmodule

reg_file_alu_tb.sv
`timescale 1ps/1ps 
`include "reg_file_alu.sv"

module reg_file_alu_tb;
logic [3:0] t_RA1, t_RA2, t_WA;
logic [7:0] t_immediate, t_ALUResult, t_cpu_out;
logic [1:0] t_ALUControl;
logic t_write_enable, t_ALUSrc, clk, t_Zero;

reg_file_alu dut (t_RA1, t_RA2, t_WA, t_immediate, t_ALUControl, t_write_enable, t_ALUSrc, clk, 
                t_ALUResult, t_cpu_out, t_Zero);

initial begin
    clk = 0;
    forever #10 clk = ~clk;
end

initial begin // Apply stimulus 
  $dumpfile("reg_file_alu_tb.vcd");
  $dumpvars(0, reg_file_alu_tb);
    t_RA1 = 4'h0; t_RA2 = 4'h2; t_WA = 4'h0; t_immediate = 8'h0A; 
    t_ALUSrc = 1; t_ALUControl = 2'b10; t_write_enable = 1;
    #10 t_RA2 = 4'h1; t_WA = 4'h1;
    #10 t_immediate = 8'h07;
    #20 t_RA1 = 4'h1; t_WA = 4'h1;
    #40 t_ALUControl = 2'b11; t_WA = 4'hF;
    #20 t_immediate = 8'b10111111;
    #20 t_immediate = 8'h0; t_ALUControl = 2'b00;
    #10

$finish; // This system tasks ends the simulation 
end

initial begin // Response monitor
  $monitor ("t = %3d, RA1 = %d RA2 = %d WA = %d Immediate = %d clk = %d write_enable = %d alusRC = %d alucontrol = %d aluresult = %d cpu_out = %d zero = %d",
            $time, t_RA1, t_RA2, t_WA, t_immediate, clk,  t_write_enable, t_ALUSrc, t_ALUControl, t_ALUResult, t_cpu_out, t_Zero);
end
endmodule

reg_file_alu_tb.vcd
$date
	Sat Feb 18 18:07:40 2023
$end
$version
	Icarus Verilog
$end
$timescale
	1ps
$end
$scope module reg_file_alu_tb $end
$var wire 8 ! t_cpu_out [7:0] $end
$var wire 1 " t_Zero $end
$var wire 8 # t_ALUResult [7:0] $end
$var reg 1 $ clk $end
$var reg 2 % t_ALUControl [1:0] $end
$var reg 1 & t_ALUSrc $end
$var reg 4 ' t_RA1 [3:0] $end
$var reg 4 ( t_RA2 [3:0] $end
$var reg 4 ) t_WA [3:0] $end
$var reg 8 * t_immediate [7:0] $end
$var reg 1 + t_write_enable $end
$scope module dut $end
$var wire 2 , ALUControl [1:0] $end
$var wire 1 & ALUSrc $end
$var wire 1 $ CLK $end
$var wire 4 - RA1 [3:0] $end
$var wire 4 . RA2 [3:0] $end
$var wire 4 / WA [3:0] $end
$var wire 8 0 immediate [7:0] $end
$var wire 1 + write_enable $end
$var wire 8 1 x_srcB [7:0] $end
$var wire 8 2 x_srcA [7:0] $end
$var wire 8 3 x_RD2 [7:0] $end
$var wire 8 4 cpu_out [7:0] $end
$var wire 1 " Zero $end
$var wire 8 5 ALUResult [7:0] $end
$scope module newalu $end
$var wire 2 6 ALUControl [1:0] $end
$var wire 8 7 SrcB [7:0] $end
$var wire 1 " Zero $end
$var wire 8 8 SrcA [7:0] $end
$var reg 8 9 ALUResult [7:0] $end
$upscope $end
$scope module newregfile $end
$var wire 8 : ALUResult [7:0] $end
$var wire 4 ; RA1 [3:0] $end
$var wire 4 < RA2 [3:0] $end
$var wire 8 = RD1 [7:0] $end
$var wire 8 > RD2 [7:0] $end
$var wire 4 ? WA [3:0] $end
$var wire 1 $ clk $end
$var wire 8 @ cpu_out [7:0] $end
$var wire 1 + write_enable $end
$upscope $end
$upscope $end
$upscope $end
$enddefinitions $end
#0
$dumpvars
bx @
b0 ?
bx >
b0 =
b10 <
b0 ;
b1010 :
b1010 9
b0 8
b1010 7
b10 6
b1010 5
bx 4
bx 3
b0 2
b1010 1
b1010 0
b0 /
b10 .
b0 -
b10 ,
1+
b1010 *
b0 )
b10 (
b0 '
1&
b10 %
0$
b1010 #
0"
bx !
$end
#10
b1010 3
b1010 >
b1 )
b1 /
b1 ?
b1 (
b1 .
b1 <
1$
#20
b111 #
b111 5
b111 9
b111 :
b111 1
b111 7
b111 *
b111 0
0$
#30
b111 3
b111 >
1$
#40
b1110 #
b1110 5
b1110 9
b1110 :
0$
b111 2
b111 8
b111 =
b1 '
b1 -
b1 ;
#50
b10101 #
b10101 5
b10101 9
b10101 :
b1110 2
b1110 8
b1110 =
b1110 3
b1110 >
1$
#60
0$
#70
b11100 #
b11100 5
b11100 9
b11100 :
b10101 2
b10101 8
b10101 =
b10101 3
b10101 >
1$
#80
b1110 #
b1110 5
b1110 9
b1110 :
0$
b1111 )
b1111 /
b1111 ?
b11 %
b11 ,
b11 6
#90
b1110 !
b1110 4
b1110 @
1$
#100
b1010110 #
b1010110 5
b1010110 9
b1010110 :
b10111111 1
b10111111 7
0$
b10111111 *
b10111111 0
#110
b1010110 !
b1010110 4
b1010110 @
1$
#120
1"
b0 #
b0 5
b0 9
b0 :
b0 1
b0 7
0$
b0 %
b0 ,
b0 6
b0 *
b0 0
#130
b0 !
b0 4
b0 @
1$
