reg_file.sv
module reg_file(input logic [3:0] RA1, RA2, WA, 
                input logic [7:0] ALUResult,
                input logic clk, write_enable,
                output logic [7:0] RD1, RD2, cpu_out); 
logic [7:0] rf [0:15];

assign RD1 = rf[RA1]; 
assign RD2 = rf[RA2]; 
assign cpu_out = rf[15];

initial begin
    rf[4'b0] = 8'b0;
end

always_ff @(posedge clk) 
if (write_enable && WA > 0) 
    rf[WA] <= ALUResult;

endmodule

reg_file_tb.sv
`timescale 1ps/1ps 
`include "reg_file.sv"

module reg_file_tb;
logic [3:0] RA1, RA2, WA;
logic clk, write_enable;
logic [7:0] ALUResult, RD1, RD2, cpu_out;
reg_file dut (RA1, RA2, WA, ALUResult, clk, write_enable, RD1, RD2, cpu_out);

initial begin // Generate clock signal with 20 ns period
clk = 0;
forever #10 clk = ~clk;
end

initial begin // Apply stimulus 
$dumpfile("reg_file_tb.vcd");
$dumpvars(0, reg_file_tb);
RA1 = 1; RA2 = 2; WA = 0; ALUResult = 5; write_enable = 0; 
#10 WA=0; //RESET = 0;
#15 write_enable = 1;
#20 WA = 1; ALUResult = 7;
#20 WA = 5; ALUResult = 13;
#20 write_enable = 0;
#20 RA2 = 5;
#30;
$finish; // This system tasks ends the simulation 
end

initial begin // Response monitor
  $monitor ("t_RA1 = %d t_RA2 = %d t_WA = %d ALUResult = %d t_clk = %d t_write_enable = %d t_RD1 = %d t_RD2 = %d",
            RA1, RA2, WA, ALUResult, clk,  write_enable, RD1, RD2);
end
endmodule

reg_file_tb.vcd
$date
	Sat Feb 18 16:54:42 2023
$end
$version
	Icarus Verilog
$end
$timescale
	1ps
$end
$scope module reg_file_tb $end
$var wire 8 ! cpu_out [7:0] $end
$var wire 8 " RD2 [7:0] $end
$var wire 8 # RD1 [7:0] $end
$var reg 8 $ ALUResult [7:0] $end
$var reg 4 % RA1 [3:0] $end
$var reg 4 & RA2 [3:0] $end
$var reg 4 ' WA [3:0] $end
$var reg 1 ( clk $end
$var reg 1 ) write_enable $end
$scope module dut $end
$var wire 8 * ALUResult [7:0] $end
$var wire 4 + RA1 [3:0] $end
$var wire 4 , RA2 [3:0] $end
$var wire 8 - RD1 [7:0] $end
$var wire 8 . RD2 [7:0] $end
$var wire 4 / WA [3:0] $end
$var wire 1 ( clk $end
$var wire 8 0 cpu_out [7:0] $end
$var wire 1 ) write_enable $end
$upscope $end
$upscope $end
$enddefinitions $end
#0
$dumpvars
bx 0
b0 /
bx .
bx -
b10 ,
b1 +
b101 *
0)
0(
b0 '
b10 &
b1 %
b101 $
bx #
bx "
bx !
$end
#10
1(
#15
1)
#20
0(
#30
1(
#35
b111 $
b111 *
b1 '
b1 /
#40
0(
#50
b111 #
b111 -
1(
#55
b1101 $
b1101 *
b101 '
b101 /
#60
0(
#70
1(
#75
0)
#80
0(
#85
b1101 "
b1101 .
b101 &
b101 ,
#90
1(
#100
0(
#105
1)
b1111 '
b1111 /
#110
b1101 !
b1101 0
1(
#115
b1111 $
b1111 *
#120
0(
#130
b1111 !
b1111 0
1(
